pyiohat/__init__.py
pyiohat/unify.py
pyiohat/utils.py
pyiohat/version.txt
pyiohat/parsers/__init__.py
pyiohat/parsers/base_parser.py
pyiohat/parsers/ident_base_parser.py
pyiohat/parsers/misc.py
pyiohat/parsers/quant_base_parser.py
pyiohat/parsers/ident/__init__.py
pyiohat/parsers/ident/comet_2020_01_4_parser.py
pyiohat/parsers/ident/dummy_parser.py
pyiohat/parsers/ident/mascot_2_6_2_parser.py
pyiohat/parsers/ident/msamanda_2_parser.py
pyiohat/parsers/ident/msfragger_3_parser.py
pyiohat/parsers/ident/msfragger_4_parser.py
pyiohat/parsers/ident/msgfplus_2021_03_22_parser.py
pyiohat/parsers/ident/omssa_2_1_9_parser.py
pyiohat/parsers/ident/xtandem_alanine.py
pyiohat/parsers/models/base_parser_model.json
pyiohat/parsers/models/ident_parser_model.json
pyiohat/parsers/models/quant_parser_model.json
pyiohat/parsers/quant/__init__.py
pyiohat/parsers/quant/flash_lfq_1_2_0_parser.py
pyiohat/parsers/quant/tmt_quant_parser_1_0_0.py
pyiohat-1.9.0.dist-info/licenses/AUTHORS.TXT
pyiohat-1.9.0.dist-info/licenses/LICENSE
pyiohat-1.9.0.dist-info/METADATA
pyiohat-1.9.0.dist-info/WHEEL
pyiohat-1.9.0.dist-info/top_level.txt
pyiohat-1.9.0.dist-info/RECORD
