Metadata-Version: 2.4
Name: pyiohat
Version: 1.9.0
Summary: Python Mass Spectrometry Input Output Harmonization Tool
Home-page: https://github.com/computational-ms/pyiohat
Author: Tristan Ranff, Manuel Kösters, Artyom Vlasov, Christian Fufezan
Author-email: christian@fufezan.net
License: MIT
Classifier: Development Status :: 4 - Beta
Classifier: Environment :: Console
Classifier: Intended Audience :: Education
Classifier: Intended Audience :: Science/Research
Classifier: Intended Audience :: Developers
Classifier: License :: OSI Approved :: Apache Software License
Classifier: Operating System :: MacOS :: MacOS X
Classifier: Operating System :: Microsoft :: Windows
Classifier: Operating System :: POSIX
Classifier: Operating System :: POSIX :: SunOS/Solaris
Classifier: Operating System :: Unix
Classifier: Programming Language :: Python :: 3.8
Classifier: Programming Language :: Python :: 3.9
Classifier: Programming Language :: Python :: 3.10
Classifier: Programming Language :: Python :: 3.11
Classifier: Topic :: Scientific/Engineering :: Bio-Informatics
Classifier: Topic :: Scientific/Engineering :: Chemistry
Classifier: Topic :: Scientific/Engineering :: Medical Science Apps.
License-File: LICENSE
License-File: AUTHORS.TXT
Requires-Dist: unimod-mapper~=0.6.8
Requires-Dist: peptide-mapper~=0.4.3
Requires-Dist: chemical-composition~=1.0.6
Requires-Dist: pyahocorasick<2.3.0,>=1.4.4
Requires-Dist: pandas<2.4.0,>=1.4.3
Requires-Dist: numpy>=1.22.0
Requires-Dist: loguru<0.8,>=0.6
Requires-Dist: tqdm
Requires-Dist: regex<2025.8.0,>=2022.7.25
Requires-Dist: uparma<1.1.0,>=0.9.15
Requires-Dist: IsoSpecPy~=2.2.0
Provides-Extra: docs
Requires-Dist: sphinx; extra == "docs"
Requires-Dist: sphinx-rtd-theme; extra == "docs"
Dynamic: license-file
